[
  {
    "x": 714,
    "y": 1026,
    "dt": 650
  },
  {
    "x": 744,
    "y": 989,
    "dt": 39
  },
  {
    "x": 793,
    "y": 937,
    "dt": 8
  },
  {
    "x": 912,
    "y": 819,
    "dt": 40
  },
  {
    "x": 975,
    "y": 753,
    "dt": 30
  },
  {
    "x": 1040,
    "y": 683,
    "dt": 26
  },
  {
    "x": 1099,
    "y": 636,
    "dt": 31
  },
  {
    "x": 1129,
    "y": 617,
    "dt": 43
  },
  {
    "x": 1138,
    "y": 611,
    "dt": 26
  },
  {
    "x": 1151,
    "y": 598,
    "dt": 27
  },
  {
    "x": 1175,
    "y": 581,
    "dt": 31
  },
  {
    "x": 1222,
    "y": 546,
    "dt": 32
  },
  {
    "x": 1245,
    "y": 525,
    "dt": 29
  },
  {
    "x": 1246,
    "y": 524,
    "dt": 155
  },
  {
    "x": 1247,
    "y": 524,
    "dt": 14
  },
  {
    "x": 1248,
    "y": 522,
    "dt": 48
  }
]